{"easy-bot-0": [5, 9, 8, 6, 19, 12, 4, 14, 11, 12], "easy-bot-1": [10, 12, 6, 8, 9, 15, 12, 13, 5, 10], "easy-bot-2": [12, 8, 7, 13, 13, 9, 6, 6, 7, 19], "easy-bot-3": [9, 7, 10, 12, 14, 10, 8, 7, 13, 10], "easy-bot-4": [11, 10, 8, 17, 13, 3, 10, 8, 10, 10], "easy-bot-5": [12, 10, 12, 11, 13, 5, 10, 5, 6, 16], "easy-bot-6": [9, 6, 8, 10, 11, 6, 10, 9, 14, 17], "easy-bot-7": [9, 16, 10, 8, 9, 9, 7, 9, 11, 12], "easy-bot-8": [8, 11, 4, 12, 10, 11, 4, 14, 13, 13], "easy-bot-9": [8, 9, 11, 8, 10, 10, 9, 11, 6, 18], "easy-bot-10": [12, 7, 10, 11, 7, 10, 7, 9, 10, 17], "easy-bot-11": [13, 7, 11, 7, 11, 5, 8, 14, 10, 14], "easy-bot-12": [10, 8, 10, 12, 8, 8, 6, 13, 9, 16], "easy-bot-13": [7, 10, 9, 12, 7, 10, 11, 7, 15, 12], "easy-bot-14": [20, 6, 12, 8, 11, 7, 8, 11, 6, 11], "easy-bot-15": [9, 10, 7, 9, 15, 7, 8, 12, 8, 15], "easy-bot-16": [9, 5, 6, 9, 9, 11, 15, 12, 7, 17], "easy-bot-17": [4, 9, 10, 13, 15, 9, 8, 9, 12, 11], "easy-bot-18": [10, 8, 15, 10, 7, 10, 5, 15, 8, 12], "easy-bot-19": [11, 5, 8, 11, 7, 12, 16, 12, 5, 13], "easy-bot-20": [12, 9, 14, 3, 10, 9, 10, 7, 9, 17], "easy-bot-21": [17, 12, 7, 7, 8, 8, 10, 7, 12, 12], "easy-bot-22": [11, 6, 7, 12, 11, 9, 12, 11, 10, 11], "easy-bot-23": [13, 8, 6, 10, 10, 7, 7, 8, 9, 22], "easy-bot-24": [6, 12, 10, 6, 17, 7, 8, 7, 12, 15], "easy-bot-25": [8, 6, 7, 15, 8, 10, 8, 12, 8, 18], "easy-bot-26": [11, 10, 6, 14, 10, 6, 8, 10, 5, 20], "easy-bot-27": [10, 6, 10, 8, 15, 14, 5, 14, 7, 11], "easy-bot-28": [14, 9, 8, 9, 6, 9, 10, 10, 8, 17], "easy-bot-29": [10, 10, 7, 10, 9, 14, 12, 7, 6, 15], "easy-bot-30": [6, 6, 12, 14, 7, 10, 11, 19, 7, 8], "easy-bot-31": [7, 10, 9, 15, 13, 11, 12, 4, 10, 9], "easy-bot-32": [11, 11, 10, 9, 8, 8, 7, 8, 13, 15], "easy-bot-33": [13, 8, 10, 14, 7, 6, 6, 11, 14, 11], "easy-bot-34": [9, 11, 10, 6, 7, 12, 12, 9, 7, 17], "easy-bot-35": [7, 15, 9, 9, 10, 11, 8, 9, 7, 15], "easy-bot-36": [8, 14, 8, 11, 10, 14, 8, 9, 8, 10], "easy-bot-37": [13, 12, 11, 7, 14, 7, 8, 9, 4, 15], "easy-bot-38": [11, 8, 14, 12, 6, 5, 11, 6, 12, 15], "easy-bot-39": [10, 10, 9, 6, 11, 15, 9, 6, 9, 15], "easy-bot-40": [7, 12, 8, 10, 6, 11, 11, 9, 14, 12], "easy-bot-41": [9, 11, 10, 6, 10, 9, 12, 12, 8, 13], "easy-bot-42": [9, 9, 13, 10, 11, 7, 6, 13, 6, 16], "easy-bot-43": [8, 10, 8, 16, 11, 5, 8, 11, 11, 12], "easy-bot-44": [6, 9, 11, 18, 8, 12, 8, 9, 6, 13], "easy-bot-45": [7, 8, 11, 7, 6, 6, 8, 22, 9, 16], "easy-bot-46": [9, 10, 10, 12, 13, 7, 7, 11, 7, 14], "easy-bot-47": [6, 12, 11, 8, 17, 4, 9, 12, 10, 11], "easy-bot-48": [10, 11, 10, 9, 6, 14, 10, 9, 10, 11], "easy-bot-49": [14, 8, 6, 19, 7, 8, 12, 7, 5, 14], "easy-bot-50": [16, 3, 12, 7, 8, 6, 8, 9, 10, 21], "easy-bot-51": [8, 11, 12, 11, 10, 8, 13, 4, 10, 13], "easy-bot-52": [16, 9, 6, 10, 8, 6, 7, 11, 8, 19], "easy-bot-53": [6, 9, 9, 7, 9, 8, 15, 10, 12, 15], "easy-bot-54": [13, 10, 5, 4, 12, 13, 11, 14, 6, 12], "easy-bot-55": [17, 11, 9, 10, 4, 9, 7, 8, 9, 16], "easy-bot-56": [8, 7, 12, 11, 11, 9, 9, 9, 10, 14], "easy-bot-57": [7, 7, 9, 8, 13, 8, 9, 15, 5, 19], "easy-bot-58": [8, 11, 5, 6, 9, 11, 13, 18, 7, 12], "easy-bot-59": [8, 7, 12, 8, 7, 13, 13, 9, 8, 15], "easy-bot-60": [7, 9, 15, 8, 8, 8, 8, 13, 7, 17], "easy-bot-61": [10, 8, 10, 12, 6, 6, 9, 9, 11, 19], "easy-bot-62": [10, 8, 10, 9, 10, 7, 9, 8, 11, 18], "easy-bot-63": [9, 14, 10, 8, 9, 7, 8, 9, 11, 15], "easy-bot-64": [9, 8, 9, 15, 5, 10, 12, 8, 9, 15], "easy-bot-65": [10, 13, 10, 9, 7, 6, 12, 10, 8, 15], "easy-bot-66": [15, 8, 10, 11, 8, 9, 7, 12, 9, 11], "easy-bot-67": [11, 7, 16, 7, 6, 9, 10, 9, 7, 18], "easy-bot-68": [9, 9, 13, 5, 6, 15, 13, 9, 10, 11], "easy-bot-69": [10, 7, 9, 10, 9, 11, 6, 13, 9, 16], "easy-bot-70": [8, 9, 9, 11, 7, 7, 8, 11, 16, 14], "easy-bot-71": [13, 13, 6, 9, 8, 5, 18, 8, 5, 15], "easy-bot-72": [6, 8, 8, 7, 10, 18, 11, 18, 8, 6], "easy-bot-73": [11, 12, 10, 10, 7, 11, 9, 7, 6, 17], "easy-bot-74": [20, 6, 7, 7, 8, 10, 6, 9, 12, 15], "easy-bot-75": [14, 12, 6, 10, 7, 7, 6, 15, 7, 16], "easy-bot-76": [7, 11, 13, 8, 9, 13, 8, 8, 8, 15], "easy-bot-77": [13, 9, 13, 5, 13, 10, 8, 9, 5, 15], "easy-bot-78": [9, 13, 14, 5, 13, 9, 7, 9, 12, 9], "easy-bot-79": [5, 13, 10, 9, 12, 7, 12, 9, 7, 16], "easy-bot-80": [11, 13, 11, 9, 7, 10, 7, 10, 11, 11], "easy-bot-81": [11, 4, 8, 10, 12, 16, 6, 8, 12, 13], "easy-bot-82": [18, 15, 7, 10, 4, 7, 7, 11, 9, 12], "easy-bot-83": [10, 7, 5, 6, 8, 8, 14, 6, 10, 26], "easy-bot-84": [13, 11, 10, 10, 5, 11, 11, 7, 5, 17], "easy-bot-85": [11, 5, 7, 9, 8, 7, 13, 7, 9, 24], "easy-bot-86": [10, 13, 7, 7, 10, 6, 15, 6, 11, 15], "easy-bot-87": [7, 11, 10, 11, 6, 14, 11, 8, 8, 14], "easy-bot-88": [9, 11, 8, 8, 7, 17, 8, 7, 13, 12], "easy-bot-89": [13, 15, 13, 7, 6, 7, 11, 8, 8, 12], "easy-bot-90": [12, 10, 10, 3, 11, 13, 13, 7, 9, 12], "easy-bot-91": [13, 10, 5, 13, 8, 6, 11, 7, 9, 18], "easy-bot-92": [6, 5, 20, 11, 7, 8, 15, 6, 10, 12], "easy-bot-93": [10, 10, 7, 10, 5, 18, 12, 5, 10, 13], "easy-bot-94": [6, 9, 10, 9, 13, 6, 7, 10, 15, 15], "easy-bot-95": [6, 8, 5, 14, 7, 5, 13, 5, 12, 25], "easy-bot-96": [9, 5, 8, 14, 6, 15, 6, 11, 11, 15], "easy-bot-97": [12, 3, 11, 8, 11, 16, 5, 10, 13, 11], "easy-bot-98": [7, 12, 9, 5, 11, 12, 6, 6, 13, 19], "easy-bot-99": [10, 7, 9, 4, 8, 12, 12, 8, 11, 19], "dcc99bb7-98e2-4e00-b1ab-168190a99ba8": [-10, -10, -10, -10, -10, 10, 10, 30, 50, 50], "models-quick-chunky-cardinality-stagger-5de2f6": [0, 0, 0, 0, 0, 27, 14, 18, 14, 27], "internal-or-\"organic\"-sources-slow-flat-class-sway-e7a54a": [1, 1, 1, 5, 1, 1, 15, 25, 10, 40], "globally-speedy-flat-powerset-turn-9e726d": [10, 10, 10, 10, 10, 10, 10, 10, 10, 10], "holisticly-instant-skinny-limit-run-f32167": [10, 10, 10, 10, 10, 10, 10, 10, 10, 10], "ubiquitous-hasty-straight-universe-march-7afde8": [10, 10, 10, 10, 10, 10, 10, 10, 10, 10], "resource-maximizing-slow-round-superset-crouch-1c9b93": [4, 5, 6, 7, 8, 12, 13, 14, 15, 16], "morph-sluggish-fat-pair-hurry-c706b6": [10, 10, 10, 10, 10, 10, 10, 10, 10, 10], "orchestrate-sluggish-broad-union-crawl-5807bb": [4, 4, 4, 4, 4, 16, 16, 16, 16, 16], "globally-prompt-thick-cardinality-gallop-01450c": [8, 8, 8, 4, 3, 2, 14, 18, 13, 22], "implement-slow-boxy-union-crouch-1a62e7": [8, 8, 8, -4, 1, 3, 9, 24, 19, 24], "re-engineer-speedy-straight-complement-amble-2a993a": [8, 8, 8, 5, 3, 2, 11, 14, 16, 25], "opportunities-quick-solid-union-spin-c54faa": [8, 8, 8, 12, 8, 12, 8, 12, 12, 12], "scenarios-speedy-compact-limit-hurry-58a103": [8, 8, 8, 11, 11, 11, 11, 11, 11, 10], "viral-fast-bent-union-spin-280432": [10, 10, 10, 10, 10, 10, 10, 10, 10, 10], "mid-bot-0": [8, 8, 8, 5, 10, 7, 21, 7, 19, 7], "progressively-nimble-solid-superset-sit-5e42b7": [10, 10, 10, 10, 10, 10, 10, 10, 10, 10], "multimedia-based-instant-thin-member-roam-d7e970": [8, 8, 8, 8, 12, 12, 12, 11, 11, 10], "mid-bot-1": [8, 8, 8, 8, 7, 10, 27, 4, 19, 1], "unique-express-broad-union-dash-fe566c": [8, 8, 8, 8, 11, 12, 11, 12, 11, 11], "mid-bot-3": [1, 1, 1, 1, 1, 18, 20, 27, 29, 1], "low-risk-high-yield-late-straight-powerset-crouch-e7bc9d": [0, 0, 0, 1, 1, 21, 22, 22, 32, 1], "mid-bot-2": [8, 8, 8, 8, 8, 6, 20, 7, 22, 5], "front-end-instant-fat-poset-ramble-30fb97": [10, 10, 10, 10, 10, 10, 10, 10, 10, 10], "global-fast-thick-cardinality-gallop-9a089d": [0, 0, 0, 14, 0, 0, 26, 28, 32, 0], "scale-hasty-bent-limit-ramble-1dfdab": [2, 2, 3, 3, 6, 20, 12, 20, 20, 12], "sherlock": [70, 4, 4, 4, 3, 3, 3, 3, 3, 3], "out-of-the-box-hasty-bent-subset-stroll-9c4ec9": [10, 10, 10, 10, 10, 10, 10, 10, 10, 10], "matrix-swift-rounded-tuple-march-df75d0": [10, 10, 10, 10, 10, 10, 10, 10, 10, 10]}